GoBiaozhunKuZhongwenCankao/README.md
GoBiaozhunKuZhongwenCankao/__init__.py
GoBiaozhunKuZhongwenCankao/__main__.py
GoBiaozhunKuZhongwenCankao/file.epub
GoBiaozhunKuZhongwenCankao/index.html
GoBiaozhunKuZhongwenCankao/css/__init__.py
GoBiaozhunKuZhongwenCankao/css/annotations.css
GoBiaozhunKuZhongwenCankao/css/main.css
GoBiaozhunKuZhongwenCankao/css/normalize.css
GoBiaozhunKuZhongwenCankao/css/popup.css
GoBiaozhunKuZhongwenCankao/font/__init__.py
GoBiaozhunKuZhongwenCankao/font/fontello.eot
GoBiaozhunKuZhongwenCankao/font/fontello.svg
GoBiaozhunKuZhongwenCankao/font/fontello.ttf
GoBiaozhunKuZhongwenCankao/font/fontello.woff
GoBiaozhunKuZhongwenCankao/img/__init__.py
GoBiaozhunKuZhongwenCankao/img/annotator-glyph-sprite.png
GoBiaozhunKuZhongwenCankao/img/annotator-icon-sprite.png
GoBiaozhunKuZhongwenCankao/img/apple-touch-icon.png
GoBiaozhunKuZhongwenCankao/img/cancelfullscreen.png
GoBiaozhunKuZhongwenCankao/img/close.png
GoBiaozhunKuZhongwenCankao/img/fullscreen.png
GoBiaozhunKuZhongwenCankao/img/loader.gif
GoBiaozhunKuZhongwenCankao/img/menu-icon.png
GoBiaozhunKuZhongwenCankao/img/save.png
GoBiaozhunKuZhongwenCankao/img/saved.png
GoBiaozhunKuZhongwenCankao/img/settings-s.png
GoBiaozhunKuZhongwenCankao/img/settings.png
GoBiaozhunKuZhongwenCankao/img/star.png
GoBiaozhunKuZhongwenCankao/js/__init__.py
GoBiaozhunKuZhongwenCankao/js/epub.js
GoBiaozhunKuZhongwenCankao/js/epub.min.js
GoBiaozhunKuZhongwenCankao/js/epub.min.map
GoBiaozhunKuZhongwenCankao/js/hooks.min.js
GoBiaozhunKuZhongwenCankao/js/hooks.min.map
GoBiaozhunKuZhongwenCankao/js/reader.js
GoBiaozhunKuZhongwenCankao/js/reader.js.map
GoBiaozhunKuZhongwenCankao/js/reader.min.js
GoBiaozhunKuZhongwenCankao/js/reader.min.map
GoBiaozhunKuZhongwenCankao/js/hooks/__init__.py
GoBiaozhunKuZhongwenCankao/js/hooks/extensions/__init__.py
GoBiaozhunKuZhongwenCankao/js/hooks/extensions/highlight.js
GoBiaozhunKuZhongwenCankao/js/libs/__init__.py
GoBiaozhunKuZhongwenCankao/js/libs/jquery.min.js
go_biaozhun_ku_zhongwen_cankao-2024.3.1.0.dist-info/METADATA
go_biaozhun_ku_zhongwen_cankao-2024.3.1.0.dist-info/WHEEL
go_biaozhun_ku_zhongwen_cankao-2024.3.1.0.dist-info/entry_points.txt
go_biaozhun_ku_zhongwen_cankao-2024.3.1.0.dist-info/top_level.txt
go_biaozhun_ku_zhongwen_cankao-2024.3.1.0.dist-info/RECORD
